{
  "sites": [
    {
      "key": "drpy_js_豆瓣",
      "name": "豆瓣 | 热播[js]",
      "type": 3,
      "api": "https://ghproxy.com/https://raw.githubusercontent.com/hjdhnx/dr_py/main/libs/drpy2.min.js",
      "ext": "https://ghproxy.com/https://raw.githubusercontent.com/hjdhnx/dr_py/main/js/drpy.js"
    },
    {
    "key": "6v磁力",
    "name": "6v磁力",
    "type": 3,
    "searchable": 1,
    "changeable": 1,
    "api": "https://ghproxy.com/https://raw.githubusercontent.com/hjdhnx/dr_py/main/libs/drpy2.min.js",
    "ext": "https://ghproxy.com/https://raw.githubusercontent.com/hjdhnx/dr_py/main/js/6V%E6%96%B0%E7%89%88%5B%E7%A3%81%5D.js"
    },
        {
    "key": "磁力熊",
    "name": "磁力熊",
    "type": 3,
    "searchable": 1,
    "changeable": 1,
    "api": "https://ghproxy.com/https://raw.githubusercontent.com/hjdhnx/dr_py/main/libs/drpy2.min.js",
    "ext": "https://ghproxy.com/https://raw.githubusercontent.com/hjdhnx/dr_py/main/js/%E7%A3%81%E5%8A%9B%E7%86%8A%5B%E7%A3%81%5D.js"
    },
    {
    "key": "lf_js_p2p",
    "name": "磁力 | lf_p2p",
    "type": 3,
    "searchable": 1,
    "changeable": 1,
    "quickSearch": 1,
    "filterable": 1, 
    "api": "https://gh-proxy.com/https://raw.githubusercontent.com/wsy926474968/wsy926474968/main/lf_p2p1_2_min.js",
    "ext": ""
    },
      {
    "key": "lf_js_search",
    "name": "搜索 | lf_search",
    "type": 3,
    "searchable": 0,
    "changeable": 1,
    "quickSearch": 0,
    "filterable": 1,
    "api": "https://gh-proxy.com/https://raw.githubusercontent.com/wsy926474968/wsy926474968/main/lf_ikanbot3_2_min.js"
},
    {
    "key": "lf_js_ikanbot",
    "name": "点播 | lf_ikanbot",
    "type": 3,
    "searchable": 1,
    "changeable": 1,
    "quickSearch": 1,
    "filterable": 1,
    "api": "https://gh-proxy.com/https://raw.githubusercontent.com/wsy926474968/wsy926474968/main/lf_ikanbot3_2_min.js"
    }
  ]
}
